lib/__init__.py
lib/dataclasses/__init__.py
lib/dataclasses/consts.py
lib/dataclasses/entry.py
lib/dataclasses/errors.py
lib/dataclasses/json.py
lib/dataclasses/registry.py
lib/dataclasses/type_system.py
py_serializable_dataclass-0.1.3.data/scripts/publish.py
serializable_dataclass/__init__.py
serializable_dataclass/dataclasses/__init__.py
serializable_dataclass/dataclasses/consts.py
serializable_dataclass/dataclasses/entry.py
serializable_dataclass/dataclasses/errors.py
serializable_dataclass/dataclasses/json.py
serializable_dataclass/dataclasses/registry.py
serializable_dataclass/dataclasses/type_system.py
py_serializable_dataclass-0.1.3.dist-info/LICENSE
py_serializable_dataclass-0.1.3.dist-info/METADATA
py_serializable_dataclass-0.1.3.dist-info/WHEEL
py_serializable_dataclass-0.1.3.dist-info/top_level.txt
py_serializable_dataclass-0.1.3.dist-info/RECORD
